oarepo_model_builder_ui/__init__.py
oarepo_model_builder_ui/config.py
oarepo_model_builder_ui/builders/__init__.py
oarepo_model_builder_ui/builders/i18n.py
oarepo_model_builder_ui/builders/i18n_setup_cfg.py
oarepo_model_builder_ui/builders/layout.py
oarepo_model_builder_ui/builders/layout_setup_cfg.py
oarepo_model_builder_ui/datatypes/__init__.py
oarepo_model_builder_ui/datatypes/validation.py
oarepo_model_builder_ui/datatypes/components/__init__.py
oarepo_model_builder_ui/datatypes/components/model.py
oarepo_model_builder_ui/outputs/i18n.py
oarepo_model_builder_ui/outputs/layout.py
oarepo_model_builder_ui/validation/__init__.py
oarepo_model_builder_ui-4.0.10.dist-info/METADATA
oarepo_model_builder_ui-4.0.10.dist-info/WHEEL
oarepo_model_builder_ui-4.0.10.dist-info/entry_points.txt
oarepo_model_builder_ui-4.0.10.dist-info/top_level.txt
oarepo_model_builder_ui-4.0.10.dist-info/RECORD
