Metadata-Version: 2.1
Name: oarepo-model-builder-ui
Version: 4.0.10
Summary: Model builder plugin for oarepo-ui
Requires-Dist: langcodes >=3.3.0
Requires-Dist: oarepo-model-builder >=4.0.0
Requires-Dist: polib
Requires-Dist: pydantic <2.0.0
Requires-Dist: inflect <=6.0.4
Provides-Extra: tests
Requires-Dist: pytest >=7 ; extra == 'tests'
